gitinspector/__init__.py
gitinspector/basedir.py
gitinspector/blame.py
gitinspector/changes.py
gitinspector/clone.py
gitinspector/comment.py
gitinspector/config.py
gitinspector/extensions.py
gitinspector/filtering.py
gitinspector/format.py
gitinspector/gitinspector.py
gitinspector/gravatar.py
gitinspector/help.py
gitinspector/interval.py
gitinspector/localization.py
gitinspector/metrics.py
gitinspector/optval.py
gitinspector/outputable.py
gitinspector/responsibilities.py
gitinspector/terminal.py
gitinspector/timeline.py
gitinspector/version.py
gitinspector/html/flot.zip
gitinspector/html/gitinspector_piclet.png
gitinspector/html/html.footer
gitinspector/html/html.header
gitinspector/html/jquery.tablesorter.min.js.zip
gitinspector/translations/messages.pot
gitinspector/translations/messages_de.mo
gitinspector/translations/messages_de.po
gitinspector/translations/messages_fr.mo
gitinspector/translations/messages_fr.po
gitinspector/translations/messages_it.mo
gitinspector/translations/messages_it.po
gitinspector/translations/messages_pl.mo
gitinspector/translations/messages_pl.po
gitinspector/translations/messages_sv.mo
gitinspector/translations/messages_sv.po
gitinspector/translations/messages_zh.mo
gitinspector/translations/messages_zh.po
gitinspector-0.3.2.data/data/share/doc/gitinspector/DESCRIPTION.txt
gitinspector-0.3.2.data/data/share/doc/gitinspector/LICENSE.txt
gitinspector-0.3.2.data/data/share/doc/gitinspector/README.txt
gitinspector-0.3.2.dist-info/DESCRIPTION.rst
gitinspector-0.3.2.dist-info/entry_points.txt
gitinspector-0.3.2.dist-info/METADATA
gitinspector-0.3.2.dist-info/metadata.json
gitinspector-0.3.2.dist-info/RECORD
gitinspector-0.3.2.dist-info/top_level.txt
gitinspector-0.3.2.dist-info/WHEEL
