Metadata-Version: 2.0
Name: gitinspector
Version: 0.3.2
Summary: A statistical analysis tool for git repositories.
Home-page: http://gitinspector.googlecode.com
Author: Ejwa Software
Author-email: gitinspector@ejwa.se
License: GNU GPL v3
Keywords: analysis analyzer git python statistics stats vc vcs timeline
Platform: UNKNOWN
Classifier: Development Status :: 4 - Beta
Classifier: Environment :: Console
Classifier: Intended Audience :: Developers
Classifier: License :: OSI Approved :: GNU General Public License v3 or later (GPLv3+)
Classifier: Topic :: Software Development :: Version Control
Classifier: Topic :: Utilities
